tf_coder/__init__.py
tf_coder/filter_group.py
tf_coder/filter_group_test.py
tf_coder/tensor_limits.py
tf_coder/tf_coder_main.py
tf_coder/tf_coder_utils.py
tf_coder/tf_coder_utils_test.py
tf_coder/tf_functions.py
tf_coder/tf_functions_test.py
tf_coder/version.py
tf_coder/benchmarks/__init__.py
tf_coder/benchmarks/all_benchmarks.py
tf_coder/benchmarks/all_benchmarks_test.py
tf_coder/benchmarks/autopandas_benchmarks.py
tf_coder/benchmarks/benchmark.py
tf_coder/benchmarks/benchmark_test.py
tf_coder/benchmarks/google_benchmarks.py
tf_coder/benchmarks/simple_benchmarks.py
tf_coder/benchmarks/stackoverflow_benchmarks.py
tf_coder/benchmarks/test_benchmarks.py
tf_coder/datasets/__init__.py
tf_coder/datasets/collect_tensor_data.py
tf_coder/datasets/collect_tensor_data_test.py
tf_coder/datasets/random_inputs.py
tf_coder/datasets/random_inputs_test.py
tf_coder/datasets/github/__init__.py
tf_coder/datasets/github/data_loader.py
tf_coder/datasets/github/tokenizer.py
tf_coder/datasets/github/data/tf_apis_full.tfrecord-00000-of-00001
tf_coder/models/__init__.py
tf_coder/models/tensor_features_config.py
tf_coder/models/tensor_features_model.py
tf_coder/models/trained_model/ckpt-1172.data-00000-of-00001
tf_coder/models/trained_model/ckpt-1172.index
tf_coder/models/trained_model/config.json
tf_coder/natural_language/__init__.py
tf_coder/natural_language/bag_of_words_handlers.py
tf_coder/natural_language/description_handler.py
tf_coder/natural_language/description_handler_factory.py
tf_coder/natural_language/description_handler_factory_test.py
tf_coder/natural_language/description_handler_test.py
tf_coder/natural_language/tfidf_handler.py
tf_coder/natural_language/tfidf_handler_test.py
tf_coder/value_search/__init__.py
tf_coder/value_search/all_operations.py
tf_coder/value_search/all_operations_test.py
tf_coder/value_search/colab_interface.py
tf_coder/value_search/filtered_values_cache.py
tf_coder/value_search/filtered_values_cache_test.py
tf_coder/value_search/function_operation.py
tensorflow_coder-0.0.5.dist-info/LICENSE
tensorflow_coder-0.0.5.dist-info/METADATA
tensorflow_coder-0.0.5.dist-info/WHEEL
tensorflow_coder-0.0.5.dist-info/top_level.txt
tensorflow_coder-0.0.5.dist-info/RECORD
