Metadata-Version: 2.1
Name: tensorflow-coder
Version: 0.0.5
Summary: TensorFlow Coder (TF-Coder): A Program Synthesis Tool for TensorFlow
Home-page: https://github.com/google-research/tensorflow-coder
Author: Google LLC
Author-email: no-reply@google.com
License: UNKNOWN
Keywords: tensorflow coder tf-coder program synthesis tensor manipulation programming by example
Platform: UNKNOWN
Classifier: Intended Audience :: Developers
Classifier: Intended Audience :: Education
Classifier: Intended Audience :: Science/Research
Classifier: License :: OSI Approved :: Apache Software License
Classifier: Operating System :: OS Independent
Classifier: Programming Language :: Python :: 3
Classifier: Programming Language :: Python :: 3.6
Classifier: Programming Language :: Python :: 3.7
Classifier: Programming Language :: Python :: 3.8
Classifier: Topic :: Scientific/Engineering
Classifier: Topic :: Scientific/Engineering :: Mathematics
Classifier: Topic :: Scientific/Engineering :: Artificial Intelligence
Classifier: Topic :: Software Development
Classifier: Topic :: Software Development :: Code Generators
Requires-Python: >=3
Requires-Dist: absl-py (>=0.6.1)
Requires-Dist: funcsigs (>=1.0.2)
Requires-Dist: numpy (>=1.15.4)
Requires-Dist: scikit-learn (>=0.22.2)
Requires-Dist: six (>=1.12.0)
Requires-Dist: tensorflow (>=2.2.0)
